pysignalbot/__init__.py
pysignalbot/bot.py
pysignalbot/engine.py
pysignalbot/messages.py
pysignalbot-0.2.0.dist-info/LICENSE
pysignalbot-0.2.0.dist-info/METADATA
pysignalbot-0.2.0.dist-info/WHEEL
pysignalbot-0.2.0.dist-info/RECORD
