Metadata-Version: 2.1
Name: pysignalbot
Version: 0.2.0
Summary: Python client for `signal-cli-rest-api`
Home-page: https://github.com/poterba/pysignalbot
License: MIT
Author: poterba
Maintainer: poterba
Requires-Python: >=3.9,<4.0
Classifier: License :: OSI Approved :: MIT License
Classifier: Programming Language :: Python :: 3
Classifier: Programming Language :: Python :: 3.9
Classifier: Programming Language :: Python :: 3.10
Classifier: Programming Language :: Python :: 3.11
Classifier: Programming Language :: Python :: 3.12
Requires-Dist: asyncio
Requires-Dist: dataclass-wizard
Requires-Dist: requests
Requires-Dist: websockets
Project-URL: Repository, https://github.com/poterba/pysignalbot
